consentiment/__init__.py
consentiment/consentiment.py
consentiment/eval/__init__.py
consentiment/eval/eval.py
consentiment/utils/__init__.py
consentiment/utils/utils.py
consentiment-0.5.dist-info/METADATA
consentiment-0.5.dist-info/WHEEL
consentiment-0.5.dist-info/top_level.txt
consentiment-0.5.dist-info/RECORD
