Metadata-Version: 2.1
Name: consentiment
Version: 0.5
Summary: The library for the ConSentiment graph regularization methods.
Home-page: https://github.com/GuilhermeMarcon/ConSentiment
Author: Guilherme Marcon
Author-email: guilherme.santos.marcon@alumni.usp.br
Classifier: Programming Language :: Python :: 3
Classifier: License :: OSI Approved :: MIT License
Classifier: Operating System :: OS Independent
Requires-Python: >=3.6
Requires-Dist: nervaluate ==0.1.8
